Metadata-Version: 1.0
Name: jsonic
Version: 0.1.0
Summary: Utilities for handling streams of JSON objects
Home-page: https://github.com/pcattori/jsonic
Author: Pedro Cattori
Author-email: pcattori@gmail.com
License: MIT
Platform: UNKNOWN
